setup.py
km_plugin_feishu/__init__.py
km_plugin_feishu/feishu_api.py
km_plugin_feishu.egg-info/PKG-INFO
km_plugin_feishu.egg-info/SOURCES.txt
km_plugin_feishu.egg-info/dependency_links.txt
km_plugin_feishu.egg-info/entry_points.txt
km_plugin_feishu.egg-info/requires.txt
km_plugin_feishu.egg-info/top_level.txt